bleetube_nip05er/derp_nip05er.py
bleetube_nip05er/nip05er.py
bleetube_nip05er/reports.py
bleetube_nip05er-0.1.3.dist-info/LICENSE
bleetube_nip05er-0.1.3.dist-info/METADATA
bleetube_nip05er-0.1.3.dist-info/WHEEL
bleetube_nip05er-0.1.3.dist-info/entry_points.txt
bleetube_nip05er-0.1.3.dist-info/top_level.txt
bleetube_nip05er-0.1.3.dist-info/RECORD
