Metadata-Version: 2.1
Name: bleetube-nip05er
Version: 0.1.3
Summary: Internal devops tool for managing inventory of collectors
Author-email: blee <blee@bitcoiner.social>
License: Apache License
Project-URL: Homepage, https://github.com/bleetube/nip05er
Keywords: nostr,nip05
Classifier: Programming Language :: Python
Classifier: Programming Language :: Python :: 3
Classifier: Programming Language :: Python :: 3.10
Classifier: Programming Language :: Python :: Implementation :: CPython
Classifier: Programming Language :: Python :: Implementation :: PyPy
Requires-Python: >=3.10.0
License-File: LICENSE
Requires-Dist: build (>=0.8.0)
Requires-Dist: click (>=8.1.3)
Requires-Dist: psycopg2 (>=2.9.5)
Requires-Dist: websockets (>=10.4)
Requires-Dist: python-dotenv (>=1.0.0)
